nonebot_plugin_admin_hello/__init__.py
nonebot_plugin_admin_hello/approve.py
nonebot_plugin_admin_hello/auto_ban.py
nonebot_plugin_admin_hello/auto_ban_.py
nonebot_plugin_admin_hello/config.py
nonebot_plugin_admin_hello/func_hook.py
nonebot_plugin_admin_hello/group_request_verify.py
nonebot_plugin_admin_hello/img_check.py
nonebot_plugin_admin_hello/notice.py
nonebot_plugin_admin_hello/path.py
nonebot_plugin_admin_hello/request.py
nonebot_plugin_admin_hello/request_manual.py
nonebot_plugin_admin_hello/switcher.py
nonebot_plugin_admin_hello/timesend_msg.py
nonebot_plugin_admin_hello/utils.py
nonebot_plugin_admin_hello/welcome.py
nonebot_plugin_admin_hello/word_analyze.py
nonebot_plugin_admin_hello/wordcloud.py
nonebot_plugin_admin_hello/welcome_utils/__init__.py
nonebot_plugin_admin_hello/welcome_utils/config.py
nonebot_plugin_admin_hello/welcome_utils/message_util.py
nonebot_plugin_admin_hello-0.6.5.8.dist-info/LICENSE
nonebot_plugin_admin_hello-0.6.5.8.dist-info/METADATA
nonebot_plugin_admin_hello-0.6.5.8.dist-info/WHEEL
nonebot_plugin_admin_hello-0.6.5.8.dist-info/top_level.txt
nonebot_plugin_admin_hello-0.6.5.8.dist-info/RECORD
