Metadata-Version: 2.1
Name: nonebot-plugin-admin-hello
Version: 0.6.5.8
Summary: nonebot plugin admin hello
Author: HuYihe
Author-email: 2812856215@qq.com
Requires: aiofiles
Requires: fuzzyfinder
Requires: httpx
Requires: jieba
Requires: nonebot_adapter_onebot
Requires: nonebot2
Requires: tencentcloud_sdk_python
Requires: setuptools
Requires: jinja2
Requires: pyppeteer
Requires: imageio
Requires: numpy
Requires: nonebot_plugin_apscheduler
Requires: nonebot_plugin_htmlrender
Requires: beautifulsoup4
Requires: httpx
Requires: lxml
Requires: Pillow
Requires: matplotlib
Requires: xlsxwriter
Requires: sqlitedict
Requires: aiofiles
Requires: littlepaimon_utils
Requires: requests
Requires: pydantic
License-File: LICENSE
